hydrotools/gcp_client/__init__.py
hydrotools/gcp_client/gcp.py
hydrotools/gcp_client/utils.py
hydrotools/gcp_client/data/RouteLink_CONUS_NWMv2.1.6.csv
hydrotools/gcp_client/data/RouteLink_HI.csv
hydrotools/gcp_client/data/RouteLink_NWMv2.0.csv
hydrotools/gcp_client/data/RouteLink_PuertoRico_NWMv2.1_20191204.csv
hydrotools.gcp_client-4.1.2.dist-info/LICENSE
hydrotools.gcp_client-4.1.2.dist-info/METADATA
hydrotools.gcp_client-4.1.2.dist-info/WHEEL
hydrotools.gcp_client-4.1.2.dist-info/top_level.txt
hydrotools.gcp_client-4.1.2.dist-info/RECORD
