Metadata-Version: 2.1
Name: hydrotools.gcp-client
Version: 4.1.2
Summary: Retrieve National Water Model data from Google Cloud Platform.
Home-page: https://github.com/NOAA-OWP/hydrotools
Author: Jason A. Regina
Author-email: jason.regina@noaa.gov
License: USDOC
Project-URL: Documentation, https://noaa-owp.github.io/hydrotools/hydrotools.gcp_client.html
Project-URL: Source, https://github.com/NOAA-OWP/hydrotools/tree/main/python/gcp_client
Project-URL: Tracker, https://github.com/NOAA-OWP/hydrotools/issues
Platform: UNKNOWN
Classifier: Development Status :: 3 - Alpha
Classifier: Intended Audience :: Education
Classifier: Intended Audience :: Science/Research
Classifier: License :: Free To Use But Restricted
Classifier: Programming Language :: Python :: 3.7
Classifier: Programming Language :: Python :: 3.8
Classifier: Programming Language :: Python :: 3.9
Classifier: Topic :: Scientific/Engineering :: Hydrology
Classifier: Operating System :: OS Independent
Requires-Python: >=3.7
License-File: LICENSE
Requires-Dist: numpy (>=1.20.0)
Requires-Dist: pandas
Requires-Dist: xarray
Requires-Dist: h5netcdf
Requires-Dist: hydrotools.caches (>=0.1.2)
Requires-Dist: google-cloud-storage
Provides-Extra: develop
Requires-Dist: pytest ; extra == 'develop'
